moosey_cms/.python-version
moosey_cms/__init__.py
moosey_cms/cache.py
moosey_cms/file_watcher.py
moosey_cms/filters.py
moosey_cms/helpers.py
moosey_cms/hot_reload_script.py
moosey_cms/main.py
moosey_cms/md.py
moosey_cms/models.py
moosey_cms/py.typed
moosey_cms/pyproject.toml
moosey_cms/seo.py
moosey_cms/static/js/reload-script.js
moosey_cms-0.4.0.dist-info/METADATA
moosey_cms-0.4.0.dist-info/WHEEL
moosey_cms-0.4.0.dist-info/RECORD
