Metadata-Version: 2.4
Name: moosey-cms
Version: 0.4.0
Summary: Add your description here
Requires-Python: >=3.9
Requires-Dist: cachetools>=6.2.4
Requires-Dist: fastapi>=0.128.0
Requires-Dist: inflection>=0.5.1
Requires-Dist: jinja2>=3.1.6
Requires-Dist: markdown>=3.10
Requires-Dist: pymdown-extensions>=10.20
Requires-Dist: python-frontmatter>=1.1.0
Requires-Dist: python-slugify>=8.0.4
Requires-Dist: uvicorn>=0.40.0
Requires-Dist: watchdog>=6.0.0
